Tests/__init__.py
Tests/test_file.py
Tests/test_link.py
src/DLChecker.py
src/DLFunctions.py
src/__init__.py
Dead_Link_Checker-1.0.0.dist-info/LICENSE
Dead_Link_Checker-1.0.0.dist-info/METADATA
Dead_Link_Checker-1.0.0.dist-info/WHEEL
Dead_Link_Checker-1.0.0.dist-info/entry_points.txt
Dead_Link_Checker-1.0.0.dist-info/top_level.txt
Dead_Link_Checker-1.0.0.dist-info/RECORD
