Metadata-Version: 2.1
Name: Dead-Link-Checker
Version: 1.0.0
Summary: The command line tool for checking dead link
Home-page: https://github.com/sonechca/Dead_Link_Checker
Author: Mintae Kim
Author-email: mkim221@myseneca.ca
License: MIT
Platform: UNKNOWN
Classifier: Programming Language :: Python :: 3
Classifier: License :: OSI Approved :: MIT License
Classifier: Operating System :: OS Independent
Requires-Python: >=3.6
